enahopy/__init__.py
enahopy/cli.py
enahopy/data_quality.py
enahopy/exceptions.py
enahopy/logging.py
enahopy/merger_analysis.py
enahopy/merger_analysis_report.txt
enahopy/reporting.py
enahopy/statistical_analysis.py
enahopy/validation.py
enahopy/version.py
enahopy/econometrics/__init__.py
enahopy/econometrics/causal_inference.py
enahopy/econometrics/inequality_analysis.py
enahopy/econometrics/policy_evaluation.py
enahopy/econometrics/poverty_analysis.py
enahopy/econometrics/survey_methods.py
enahopy/loader/__init__.py
enahopy/loader/core/__init__.py
enahopy/loader/core/cache.py
enahopy/loader/core/cache_benchmark.py
enahopy/loader/core/config.py
enahopy/loader/core/exceptions.py
enahopy/loader/core/logging.py
enahopy/loader/io/__init__.py
enahopy/loader/io/base.py
enahopy/loader/io/loader_benchmark.py
enahopy/loader/io/local_reader.py
enahopy/loader/io/main.py
enahopy/loader/io/downloaders/__init__.py
enahopy/loader/io/downloaders/async_downloader.py
enahopy/loader/io/downloaders/downloader.py
enahopy/loader/io/downloaders/extractor.py
enahopy/loader/io/downloaders/network.py
enahopy/loader/io/readers/__init__.py
enahopy/loader/io/readers/base.py
enahopy/loader/io/readers/csv.py
enahopy/loader/io/readers/factory.py
enahopy/loader/io/readers/parquet.py
enahopy/loader/io/readers/spss.py
enahopy/loader/io/readers/stata.py
enahopy/loader/io/validators/__init__.py
enahopy/loader/io/validators/columns.py
enahopy/loader/io/validators/enaho.py
enahopy/loader/io/validators/results.py
enahopy/loader/utils/__init__.py
enahopy/loader/utils/io_utils.py
enahopy/merger/__init__.py
enahopy/merger/config.py
enahopy/merger/convenience.py
enahopy/merger/core.py
enahopy/merger/exceptions.py
enahopy/merger/geographic/__init__.py
enahopy/merger/geographic/merger.py
enahopy/merger/geographic/patterns.py
enahopy/merger/geographic/strategies.py
enahopy/merger/geographic/validators.py
enahopy/merger/modules/__init__.py
enahopy/merger/modules/merger.py
enahopy/merger/modules/validator.py
enahopy-0.6.0.dist-info/licenses/LICENSE
enahopy-0.6.0.dist-info/METADATA
enahopy-0.6.0.dist-info/WHEEL
enahopy-0.6.0.dist-info/top_level.txt
enahopy-0.6.0.dist-info/RECORD
